setup.py
cmsplugin_shop/__init__.py
cmsplugin_shop/admin.py
cmsplugin_shop/admins.py
cmsplugin_shop/cms_app.py
cmsplugin_shop/cms_menus.py
cmsplugin_shop/cms_plugins.py
cmsplugin_shop/cms_toolbar.py
cmsplugin_shop/cms_toolbars.py
cmsplugin_shop/forms.py
cmsplugin_shop/menu.py
cmsplugin_shop/middleware.py
cmsplugin_shop/models.py
cmsplugin_shop/plugins.py
cmsplugin_shop/price.py
cmsplugin_shop/settings.py
cmsplugin_shop/tests.py
cmsplugin_shop/urls.py
cmsplugin_shop/utils.py
cmsplugin_shop/views.py
cmsplugin_shop.egg-info/PKG-INFO
cmsplugin_shop.egg-info/SOURCES.txt
cmsplugin_shop.egg-info/dependency_links.txt
cmsplugin_shop.egg-info/top_level.txt
cmsplugin_shop/locale/cs
cmsplugin_shop/locale/cs/LC_MESSAGES
cmsplugin_shop/locale/cs/LC_MESSAGES/django.mo
cmsplugin_shop/locale/cs/LC_MESSAGES/django.po
cmsplugin_shop/templates/cmsplugin_shop
cmsplugin_shop/templates/cmsplugin_shop/base.html
cmsplugin_shop/templates/cmsplugin_shop/cart.html
cmsplugin_shop/templates/cmsplugin_shop/category
cmsplugin_shop/templates/cmsplugin_shop/category.html
cmsplugin_shop/templates/cmsplugin_shop/list_categories.html
cmsplugin_shop/templates/cmsplugin_shop/list_products.html
cmsplugin_shop/templates/cmsplugin_shop/node.html
cmsplugin_shop/templates/cmsplugin_shop/order_cart.html
cmsplugin_shop/templates/cmsplugin_shop/order_customer_mail.txt
cmsplugin_shop/templates/cmsplugin_shop/order_detail.html
cmsplugin_shop/templates/cmsplugin_shop/order_details.html
cmsplugin_shop/templates/cmsplugin_shop/order_form.html
cmsplugin_shop/templates/cmsplugin_shop/order_list.html
cmsplugin_shop/templates/cmsplugin_shop/order_manager_mail.txt
cmsplugin_shop/templates/cmsplugin_shop/order_pdf.html
cmsplugin_shop/templates/cmsplugin_shop/product
cmsplugin_shop/templates/cmsplugin_shop/product.html
cmsplugin_shop/templates/cmsplugin_shop/root.html
cmsplugin_shop/templates/cmsplugin_shop/category/default.html
cmsplugin_shop/templates/cmsplugin_shop/product/default.html
cmsplugin_shop/templatetags/__init__.py
cmsplugin_shop/templatetags/shop_tags.py